cli.py
hydrus/__init__.py
hydrus/app.py
hydrus/app_factory.py
hydrus/auth.py
hydrus/conf.py
hydrus/resources.py
hydrus/utils.py
hydrus/data/__init__.py
hydrus/data/crud.py
hydrus/data/crud_helpers.py
hydrus/data/db_models.py
hydrus/data/doc_parse.py
hydrus/data/exceptions.py
hydrus/data/resource_based_classes.py
hydrus/data/user.py
hydrus/data/helpers/__init__.py
hydrus/data/helpers/item_collection_helpers.py
hydrus/data/helpers/itemhelpers.py
hydrus/data/helpers/items_helpers.py
hydrus/extensions/__init__.py
hydrus/extensions/socketio_factory.py
hydrus/extensions/stale_records_cleanup.py
hydrus/extensions/sync_namespace.py
hydrus/extensions/utils.py
hydrus/samples/__init__.py
hydrus/samples/doc_writer_sample.py
hydrus/samples/doc_writer_sample_output.py
hydrus/samples/hydra_doc_sample.py
hydrus-0.4.7.dist-info/LICENSE
hydrus-0.4.7.dist-info/METADATA
hydrus-0.4.7.dist-info/WHEEL
hydrus-0.4.7.dist-info/entry_points.txt
hydrus-0.4.7.dist-info/top_level.txt
hydrus-0.4.7.dist-info/RECORD
