Metadata-Version: 2.1
Name: hydrus
Version: 0.4.7
Summary: Hydra Ecosystem Flagship Server. Deploy REST data for Web 3.0
Home-page: https://github.com/HTTP-APIs/hydrus
Author: Hydra Ecosystem
Author-email: collective@hydraecosystem.org
License: UNKNOWN
Platform: UNKNOWN
Requires-Python: >=3.5.2
Requires-Dist: alembic (==1.0.10)
Requires-Dist: aniso8601 (==3.0.2)
Requires-Dist: appdirs (==1.4.3)
Requires-Dist: blinker (==1.4)
Requires-Dist: click (==7.1.2)
Requires-Dist: certifi (==2019.11.28)
Requires-Dist: flake8
Requires-Dist: Flask (==2.0.1)
Requires-Dist: Flask-Cors (==3.0.10)
Requires-Dist: Flask-RESTful (==0.3.9)
Requires-Dist: Flask-SocketIO (==4.2.1)
Requires-Dist: gevent (==20.12.0)
Requires-Dist: gevent-websocket (==0.10.1)
Requires-Dist: greenlet (==0.4.17)
Requires-Dist: hydra-python-core (==0.3.1)
Requires-Dist: hydra-openapi-parser
Requires-Dist: itsdangerous (==2.0.1)
Requires-Dist: Jinja2 (==3.0.1)
Requires-Dist: lifter (==0.4.1)
Requires-Dist: psycopg2-binary (==2.8.6)
Requires-Dist: pyld (==2.0.3)
Requires-Dist: pytest (==6.2.4)
Requires-Dist: Mako (==1.1.0)
Requires-Dist: MarkupSafe (==2.0.1)
Requires-Dist: packaging (==20.9)
Requires-Dist: pep8 (==1.7.1)
Requires-Dist: persisting-theory (==0.2.1)
Requires-Dist: pyparsing (==2.4.6)
Requires-Dist: python-dateutil (==2.8.1)
Requires-Dist: python-editor (==1.0.4)
Requires-Dist: python-engineio (==3.11.2)
Requires-Dist: python-socketio (==4.4.0)
Requires-Dist: pytz (==2019.3)
Requires-Dist: PyYAML (==5.4.1)
Requires-Dist: six (==1.13.0)
Requires-Dist: SQLAlchemy (==1.3.12)
Requires-Dist: thespian (==3.9.11)
Requires-Dist: Werkzeug (==2.0.1)
Requires-Dist: structlog
